DefPy
