Metadata-Version: 2.1
Name: DefPy
Version: 1.1.3
Summary: Libary for python
Author: itzkeeni.py
Author-email: maratkanovartem89@mail.ru
License: License :: OSI Approved :: MIT License
Classifier: Programming Language :: Python :: 3
Classifier: Operating System :: OS Independent
